stats386_final_movies/__init__.py
stats386_final_movies/analysis_and_visualization.py
stats386_final_movies/app.py
stats386_final_movies/dataLoading/clean_movie_data.py
stats386_final_movies/dataLoading/cleaned_movies.json
stats386_final_movies/dataLoading/getMovieData.py
stats386_final_movies/dataLoading/getMovieIDs.py
stats386_final_movies/dataLoading/movies.json
stats386_final_movies/dataLoading/peek_movies.py
386finalproject-0.1.0.dist-info/METADATA
386finalproject-0.1.0.dist-info/WHEEL
386finalproject-0.1.0.dist-info/top_level.txt
386finalproject-0.1.0.dist-info/RECORD
