Metadata-Version: 2.4
Name: 386finalproject
Version: 0.1.0
Summary: First iteration of final project for Stats 386
Requires-Python: >=3.10
Requires-Dist: ipykernel>=7.1.0
Requires-Dist: streamlit
Requires-Dist: pandas
Requires-Dist: matplotlib
Requires-Dist: seaborn
Requires-Dist: scipy
Requires-Dist: requests
